odoo/addons/l10n_es_aeat_mod349/README.rst
odoo/addons/l10n_es_aeat_mod349/__init__.py
odoo/addons/l10n_es_aeat_mod349/__manifest__.py
odoo/addons/l10n_es_aeat_mod349/data/aeat.349.map.line.csv
odoo/addons/l10n_es_aeat_mod349/data/aeat_export_mod349_data.xml
odoo/addons/l10n_es_aeat_mod349/data/aeat_export_mod349_partner_data.xml
odoo/addons/l10n_es_aeat_mod349/data/aeat_export_mod349_partner_refund_data.xml
odoo/addons/l10n_es_aeat_mod349/data/l10n.es.aeat.map.tax.line.tax.csv
odoo/addons/l10n_es_aeat_mod349/docs/BOE-A-2010-5098.pdf
odoo/addons/l10n_es_aeat_mod349/docs/NREG-349-2016.docx
odoo/addons/l10n_es_aeat_mod349/i18n/ca.po
odoo/addons/l10n_es_aeat_mod349/i18n/es.po
odoo/addons/l10n_es_aeat_mod349/i18n/l10n_es_aeat_mod349.pot
odoo/addons/l10n_es_aeat_mod349/models/__init__.py
odoo/addons/l10n_es_aeat_mod349/models/account_move.py
odoo/addons/l10n_es_aeat_mod349/models/account_tax.py
odoo/addons/l10n_es_aeat_mod349/models/aeat_349_map_line.py
odoo/addons/l10n_es_aeat_mod349/models/mod349.py
odoo/addons/l10n_es_aeat_mod349/readme/CONTRIBUTORS.md
odoo/addons/l10n_es_aeat_mod349/readme/DESCRIPTION.md
odoo/addons/l10n_es_aeat_mod349/readme/ROADMAP.md
odoo/addons/l10n_es_aeat_mod349/readme/USAGE.md
odoo/addons/l10n_es_aeat_mod349/report/aeat_mod349.xml
odoo/addons/l10n_es_aeat_mod349/report/common_templates.xml
odoo/addons/l10n_es_aeat_mod349/report/report_views.xml
odoo/addons/l10n_es_aeat_mod349/security/ir.model.access.csv
odoo/addons/l10n_es_aeat_mod349/security/mod_349_security.xml
odoo/addons/l10n_es_aeat_mod349/static/description/icon.png
odoo/addons/l10n_es_aeat_mod349/static/description/icon_source.svg
odoo/addons/l10n_es_aeat_mod349/static/description/index.html
odoo/addons/l10n_es_aeat_mod349/tests/__init__.py
odoo/addons/l10n_es_aeat_mod349/tests/test_l10n_es_aeat_mod349.py
odoo/addons/l10n_es_aeat_mod349/views/account_move_view.xml
odoo/addons/l10n_es_aeat_mod349/views/account_tax_view.xml
odoo/addons/l10n_es_aeat_mod349/views/aeat_349_map_view.xml
odoo_addon_l10n_es_aeat_mod349-18.0.1.0.2.dist-info/METADATA
odoo_addon_l10n_es_aeat_mod349-18.0.1.0.2.dist-info/WHEEL
odoo_addon_l10n_es_aeat_mod349-18.0.1.0.2.dist-info/top_level.txt
odoo_addon_l10n_es_aeat_mod349-18.0.1.0.2.dist-info/RECORD
